samutils/__init__.py
samutils/perceptron.py
samutils_pkg_Samm_G-0.0.1.dist-info/LICENSE
samutils_pkg_Samm_G-0.0.1.dist-info/METADATA
samutils_pkg_Samm_G-0.0.1.dist-info/WHEEL
samutils_pkg_Samm_G-0.0.1.dist-info/top_level.txt
samutils_pkg_Samm_G-0.0.1.dist-info/RECORD
