Metadata-Version: 2.1
Name: samutils-pkg-Samm-G
Version: 0.0.1
Summary: A small package for perceptron
Home-page: https://github.com/Samm-G/samutils-pkg
Author: Samm-G
Author-email: gsamarth97@gmail.com
Project-URL: Bug Tracker, https://github.com/Samm-G/samutils-pkg/issues
Classifier: Programming Language :: Python :: 3
Classifier: License :: OSI Approved :: MIT License
Classifier: Operating System :: OS Independent
Requires-Python: >=3.6
License-File: LICENSE
Requires-Dist: numpy (==1.21.4)
Requires-Dist: pandas (==1.3.4)
Requires-Dist: joblib (==1.1.0)
